offlinepdf/__init__.py
offlinepdf/cli.py
offlinepdf/compress.py
offlinepdf/docx2pdf.py
offlinepdf/image2pdf.py
offlinepdf/lock.py
offlinepdf/merge.py
offlinepdf/pdf2docx.py
offlinepdf/unlock.py
offlinepdf/utils.py
offlinepdf-1.0.2.dist-info/licenses/LICENSE
offlinepdf-1.0.2.dist-info/METADATA
offlinepdf-1.0.2.dist-info/WHEEL
offlinepdf-1.0.2.dist-info/entry_points.txt
offlinepdf-1.0.2.dist-info/top_level.txt
offlinepdf-1.0.2.dist-info/RECORD
