Metadata-Version: 2.4
Name: offlinepdf
Version: 1.0.2
Summary: Privacy-first CLI tool for offline PDF processing
Author: OfflinePDF Contributors
License: MIT
Project-URL: Homepage, https://github.com/Daniyal-Qureshi/offlinepdf
Project-URL: Repository, https://github.com/Daniyal-Qureshi/offlinepdf
Project-URL: Issues, https://github.com/Daniyal-Qureshi/offlinepdf/issues
Keywords: pdf,cli,privacy,local,offline
Classifier: Development Status :: 4 - Beta
Classifier: Intended Audience :: End Users/Desktop
Classifier: License :: OSI Approved :: MIT License
Classifier: Programming Language :: Python :: 3
Classifier: Programming Language :: Python :: 3.9
Classifier: Programming Language :: Python :: 3.10
Classifier: Programming Language :: Python :: 3.11
Classifier: Programming Language :: Python :: 3.12
Classifier: Topic :: Office/Business
Classifier: Topic :: Utilities
Requires-Python: >=3.11
License-File: LICENSE
Requires-Dist: typer>=0.9.0
Requires-Dist: rich>=13.0.0
Requires-Dist: pikepdf>=8.0.0
Requires-Dist: pdf2docx==0.5.6
Requires-Dist: Pillow>=10.0.0
Requires-Dist: docx2pdf>=0.1.8
Requires-Dist: PyMuPDF==1.22.5
Requires-Dist: python-docx>=1.0.0
Dynamic: license-file
